dukeai/__init__.py
dukeai/config.py
dukeai/auto/__init__.py
dukeai/auto/auto.py
dukeai/bookeeping/__init__.py
dukeai/bookeeping/bookeeping_categories.py
dukeai/bookeeping/bookkeeping_apis.py
dukeai/ocr/__init__.py
dukeai/ocr/ocr.py
dukeai/rpa/__init__.py
dukeai/rpa/rpa.py
dukeai/rpa_functions/__init__.py
dukeai/rpa_functions/get_ratecon_schemas.py
dukeai/rpa_functions/ratecon_data_check.py
dukeai/rpa_functions/ratecon_mapping.py
dukeai/rpa_functions/ratecon_schema_check.py
dukeai/rpa_functions/text_clean.py
dukeai-0.4.0.dist-info/LICENCE
dukeai-0.4.0.dist-info/METADATA
dukeai-0.4.0.dist-info/WHEEL
dukeai-0.4.0.dist-info/top_level.txt
dukeai-0.4.0.dist-info/RECORD
