Metadata-Version: 2.1
Name: dukeai
Version: 0.4.0
Summary: Dukeai Development Package
Home-page: https://duke.ai
Author: Shubham Kothari
Author-email: shubham@duke.ai
License: Apache License
Platform: linux
Platform: unix
Classifier: Programming Language :: Python :: 3
Classifier: License :: OSI Approved :: MIT License
Classifier: Operating System :: OS Independent
Requires-Python: >3.5.2
Requires-Dist: boto3
Requires-Dist: requests
Requires-Dist: colorama
